src/dice/_version.py
uob_dice-2025.3.1.dist-info/METADATA
uob_dice-2025.3.1.dist-info/WHEEL
uob_dice-2025.3.1.dist-info/RECORD
